quorum_mininode_py/__init__.py
quorum_mininode_py/api/__init__.py
quorum_mininode_py/api/base.py
quorum_mininode_py/api/lightnode.py
quorum_mininode_py/client/__init__.py
quorum_mininode_py/client/_http.py
quorum_mininode_py/client/mininode.py
quorum_mininode_py/crypto/__init__.py
quorum_mininode_py/crypto/account.py
quorum_mininode_py/crypto/aes.py
quorum_mininode_py/crypto/age.py
quorum_mininode_py/crypto/trx.py
quorum_mininode_py/proto/__init__.py
quorum_mininode_py/proto/quorum_pb2.py
quorum_mininode_py/utils/__init__.py
quorum_mininode_py/utils/url.py
quorum_mininode_py-1.3.3.dist-info/LICENSE
quorum_mininode_py-1.3.3.dist-info/METADATA
quorum_mininode_py-1.3.3.dist-info/WHEEL
quorum_mininode_py-1.3.3.dist-info/top_level.txt
quorum_mininode_py-1.3.3.dist-info/RECORD
