Metadata-Version: 2.1
Name: quorum-mininode-py
Version: 1.3.3
Summary: a mini python sdk for quorum lightnode with http/https requests to quorum fullnode
Home-page: https://github.com/liujuanjuan1984/quorum_mininode_py
Author: liujuanjuan1984, zhangwm404
Author-email: qiaoanlu@163.com
Project-URL: Github Repo, https://github.com/liujuanjuan1984/quorum_mininode_py
Project-URL: Bug Tracker, https://github.com/liujuanjuan1984/quorum_mininode_py/issues
Project-URL: About Quorum, https://github.com/rumsystem/quorum
Keywords: rumsystem,quorum,lightnode,sdk
Classifier: Programming Language :: Python :: 3
Classifier: Programming Language :: Python :: 3.9
Classifier: License :: OSI Approved :: MIT License
Classifier: Operating System :: OS Independent
Requires-Python: >=3.5
License-File: LICENSE
Requires-Dist: requests
Requires-Dist: eth-keys
Requires-Dist: pyrage
Requires-Dist: protobuf
Requires-Dist: eth-account >=0.8.0
